{
  "scripts": {
    "dev": "vite",
    "dev:api": "node scripts/dev-server.mjs",
    "build": "npm run build:client && npm run build:server",
    "build:client": "vite build",
    "build:server": "vite build --config vite.config.server.ts",
    "start": "node dist/server/node-build.mjs",
    "preview": "vite preview",
    "test": "vitest --run",
    "format.fix": "prettier --write .",
    "typecheck": "tsc",
    "db:migrate": "prisma migrate deploy",
    "db:seed": "prisma db seed",
    "db:studio": "prisma studio",
    "db:push": "prisma db push",
    "postinstall": "prisma generate"
  },
  "engines": {
    "node": ">=18.0.0",
    "npm": ">=8.0.0"
  }
}
